[
    {
        "name": "Must-Do List",
        "description": "",
        "imgLinkList": []
    },{
        "name": "IF Mobile",
        "description": "",
        "imgLinkList": []
    },{
        "name": "Vendor Pop",
        "description": "",
        "imgLinkList": []
    },{
        "name": "Swing Memory Game",
        "description": "",
        "imgLinkList": []
    },{
        "name": "React/Sass Portfolio",
        "description": "",
        "imgLinkList": []
    },{
        "name": "Engine de busca",
        "description": "",
        "imgLinkList": []
    },{
        "name": "My Book List",
        "description": "",
        "imgLinkList": []
    },{
        "name": "Naval Battle",
        "description": "",
        "imgLinkList": []
    },{
        "name": "Byte Barrage",
        "description": "",
        "imgLinkList": []
    }
]